wechat_work_webhook/__init__.py
wechat_work_webhook-0.0.2.dist-info/METADATA
wechat_work_webhook-0.0.2.dist-info/WHEEL
wechat_work_webhook-0.0.2.dist-info/top_level.txt
wechat_work_webhook-0.0.2.dist-info/RECORD
