Metadata-Version: 2.1
Name: wechat-work-webhook
Version: 0.0.2
Summary: A wechat work webhook client.
Home-page: https://github.com/mqzhang/wechat_work_webhook_py
Author: mqzhang
Author-email: zmingqian@qq.com
License: UNKNOWN
Platform: UNKNOWN
Classifier: Programming Language :: Python :: 3
Classifier: License :: OSI Approved :: MIT License
Classifier: Operating System :: OS Independent
Requires-Python: >=3.6
Requires-Dist: requests
